{"stats":{"minecraft:picked_up":{"minecraft:command_block":1,"minecraft:wheat_seeds":1,"minecraft:dandelion":1,"minecraft:acacia_pressure_plate":1,"minecraft:emerald":53},"minecraft:custom":{"minecraft:time_since_rest":220781,"minecraft:crouch_one_cm":1312,"minecraft:play_one_minute":498378,"minecraft:sprint_one_cm":2887,"minecraft:deaths":4,"minecraft:damage_taken":810,"minecraft:walk_one_cm":168227,"minecraft:sneak_time":1790,"minecraft:drop":144,"minecraft:jump":193,"minecraft:inspect_hopper":3,"minecraft:damage_dealt":152,"minecraft:leave_game":4,"minecraft:time_since_death":220751,"minecraft:climb_one_cm":8273,"minecraft:fall_one_cm":335,"minecraft:fly_one_cm":251077},"minecraft:used":{"minecraft:stone_brick_stairs":5,"minecraft:redstone_torch":9,"minecraft:glass":73,"minecraft:redstone_lamp":4,"minecraft:repeater":22,"minecraft:dirt":27,"minecraft:cobblestone":93,"minecraft:command_block":10,"minecraft:hopper":4,"minecraft:oak_slab":79,"minecraft:acacia_pressure_plate":2,"minecraft:oak_button":6,"minecraft:grass_block":25,"minecraft:redstone":7,"minecraft:oak_planks":12,"minecraft:ladder":13,"minecraft:oak_sign":21,"minecraft:stone_slab":3,"minecraft:stone_bricks":37},"minecraft:dropped":{"minecraft:command_block":1,"minecraft:grass_block":1,"minecraft:stick":2,"minecraft:emerald":140}},"DataVersion":1976}