{
  "minecraft:recipes/building_blocks/yellow_terracotta": {
    "criteria": {
      "has_terracotta": "2019-12-12 13:12:49 -0600"
    },
    "done": true
  },
  "minecraft:recipes/building_blocks/pink_terracotta": {
    "criteria": {
      "has_terracotta": "2019-12-12 13:12:49 -0600"
    },
    "done": true
  },
  "minecraft:recipes/building_blocks/lime_terracotta": {
    "criteria": {
      "has_terracotta": "2019-12-12 13:12:49 -0600"
    },
    "done": true
  },
  "minecraft:recipes/building_blocks/black_terracotta": {
    "criteria": {
      "has_terracotta": "2019-12-12 13:12:49 -0600"
    },
    "done": true
  },
  "minecraft:husbandry/root": {
    "criteria": {
      "consumed_item": "2019-12-12 13:22:59 -0600"
    },
    "done": true
  },
  "minecraft:recipes/building_blocks/purple_terracotta": {
    "criteria": {
      "has_terracotta": "2019-12-12 13:12:49 -0600"
    },
    "done": true
  },
  "minecraft:end/elytra": {
    "criteria": {
      "elytra": "2019-12-12 13:27:57 -0600"
    },
    "done": true
  },
  "minecraft:recipes/building_blocks/blue_terracotta": {
    "criteria": {
      "has_terracotta": "2019-12-12 13:12:49 -0600"
    },
    "done": true
  },
  "minecraft:recipes/building_blocks/green_terracotta": {
    "criteria": {
      "has_terracotta": "2019-12-12 13:12:49 -0600"
    },
    "done": true
  },
  "minecraft:recipes/building_blocks/cyan_terracotta": {
    "criteria": {
      "has_terracotta": "2019-12-12 13:12:49 -0600"
    },
    "done": true
  },
  "minecraft:recipes/building_blocks/snow_block": {
    "criteria": {
      "has_snowball": "2019-12-12 13:27:57 -0600"
    },
    "done": true
  },
  "minecraft:recipes/decorations/snow": {
    "criteria": {
      "has_snowball": "2019-12-12 13:27:57 -0600"
    },
    "done": true
  },
  "minecraft:recipes/building_blocks/white_terracotta": {
    "criteria": {
      "has_terracotta": "2019-12-12 13:12:49 -0600"
    },
    "done": true
  },
  "minecraft:recipes/building_blocks/red_terracotta": {
    "criteria": {
      "has_terracotta": "2019-12-12 13:12:49 -0600"
    },
    "done": true
  },
  "minecraft:recipes/building_blocks/magenta_terracotta": {
    "criteria": {
      "has_terracotta": "2019-12-12 13:12:49 -0600"
    },
    "done": true
  },
  "minecraft:recipes/building_blocks/gray_terracotta": {
    "criteria": {
      "has_terracotta": "2019-12-12 13:12:49 -0600"
    },
    "done": true
  },
  "minecraft:recipes/building_blocks/light_gray_terracotta": {
    "criteria": {
      "has_terracotta": "2019-12-12 13:12:49 -0600"
    },
    "done": true
  },
  "minecraft:recipes/building_blocks/brown_terracotta": {
    "criteria": {
      "has_terracotta": "2019-12-12 13:12:49 -0600"
    },
    "done": true
  },
  "minecraft:adventure/root": {
    "criteria": {
      "killed_by_something": "2019-12-12 13:29:55 -0600"
    },
    "done": true
  },
  "minecraft:recipes/building_blocks/orange_terracotta": {
    "criteria": {
      "has_terracotta": "2019-12-12 13:12:49 -0600"
    },
    "done": true
  },
  "minecraft:recipes/building_blocks/light_blue_terracotta": {
    "criteria": {
      "has_terracotta": "2019-12-12 13:12:49 -0600"
    },
    "done": true
  },
  "minecraft:adventure/adventuring_time": {
    "criteria": {
      "minecraft:plains": "2019-12-12 13:07:49 -0600"
    },
    "done": false
  },
  "DataVersion": 1976
}