{"stats":{"minecraft:picked_up":{"minecraft:arrow":737,"minecraft:oak_sign":1,"minecraft:orange_tulip":6,"minecraft:crossbow":10,"minecraft:red_tulip":1,"minecraft:chest":2,"minecraft:cornflower":2,"minecraft:snowball":270,"minecraft:oxeye_daisy":18},"minecraft:dropped":{"minecraft:oak_sign":1,"minecraft:orange_tulip":2,"minecraft:snowball":128},"minecraft:custom":{"minecraft:time_since_rest":6500,"minecraft:open_chest":21,"minecraft:play_one_minute":117933,"minecraft:crouch_one_cm":153,"minecraft:sprint_one_cm":847,"minecraft:damage_taken":102,"minecraft:deaths":18,"minecraft:walk_one_cm":27171,"minecraft:sneak_time":1530,"minecraft:walk_under_water_one_cm":22918,"minecraft:drop":131,"minecraft:aviate_one_cm":463563,"minecraft:jump":73,"minecraft:damage_dealt":10,"minecraft:leave_game":2,"minecraft:time_since_death":6474,"minecraft:walk_on_water_one_cm":6280,"minecraft:fall_one_cm":269,"minecraft:fly_one_cm":593550},"minecraft:used":{"minecraft:glowstone":1,"minecraft:sea_lantern":165,"minecraft:sand":13,"minecraft:cobblestone":68,"minecraft:command_block":4,"minecraft:oak_button":1,"minecraft:andesite":1,"minecraft:oak_sign":4,"minecraft:glass_pane":3,"minecraft:chest":18}},"DataVersion":1976}