{"stats":{"minecraft:used":{"minecraft:diamond_block":33,"minecraft:emerald_block":90,"minecraft:command_block":5,"minecraft:grass_block":3,"minecraft:oak_button":2,"minecraft:map":5,"minecraft:gold_block":59,"minecraft:chest":6},"minecraft:custom":{"minecraft:time_since_rest":47985,"minecraft:open_chest":9,"minecraft:crouch_one_cm":35,"minecraft:play_one_minute":50438,"minecraft:sprint_one_cm":1681,"minecraft:deaths":1,"minecraft:damage_taken":1020,"minecraft:walk_one_cm":35483,"minecraft:sneak_time":446,"minecraft:walk_under_water_one_cm":2946,"minecraft:drop":33,"minecraft:aviate_one_cm":919287,"minecraft:jump":69,"minecraft:leave_game":1,"minecraft:walk_on_water_one_cm":3020,"minecraft:time_since_death":47954,"minecraft:fall_one_cm":11761,"minecraft:fly_one_cm":106619},"minecraft:picked_up":{"minecraft:stick":1},"minecraft:dropped":{"minecraft:snowball":32,"minecraft:emerald":1}},"DataVersion":1976}